{
    "KHDL15A": [
        {
            "19489471":[
                {
                    "name_code": 2113431,
                    "score_10": 8
                },
                {
                    "name_code": 2120405,
                    "score_10": 9
                },
                {
                    "name_code": 2120501,
                    "score_10": 10
                }
            ],
            "19527801":[
                {
                    "name_code": 2113431,
                    "score_10": 8
                },
                {
                    "name_code": 2120405,
                    "score_10": 9
                },
                {
                    "name_code": 2120501,
                    "score_10": 10
                }
            ]
        }
    ],
    "KHDL16A":[
        {
            "20078291":[
                {
                    "name_code": 2113431,
                    "score_10": 8
                },
                {
                    "name_code": 2120405,
                    "score_10": 9
                },
                {
                    "name_code": 2120501,
                    "score_10": 10
                }
            ],
            "20020541":[
                {
                    "name_code": 2113431,
                    "score_10": 8
                },
                {
                    "name_code": 2120405,
                    "score_10": 9
                },
                {
                    "name_code": 2120501,
                    "score_10": 10
                }
            ]
        }
    ]
}